sdeval/__init__.py
sdeval/config/__init__.py
sdeval/config/meta.py
sdeval/controllability/__init__.py
sdeval/controllability/bikini_plus.py
sdeval/corrupt/__init__.py
sdeval/corrupt/aicorrupt.py
sdeval/fidelity/__init__.py
sdeval/fidelity/ccip.py
sdeval/utils/__init__.py
sdeval/utils/images.py
sdeval/utils/tqdm_.py
sdeval-0.0.3.dist-info/LICENSE
sdeval-0.0.3.dist-info/METADATA
sdeval-0.0.3.dist-info/WHEEL
sdeval-0.0.3.dist-info/top_level.txt
sdeval-0.0.3.dist-info/RECORD
